pqagent/__init__.py
pqagent/metrics.py
pqagent/mlp.py
pqagent/pqagent.py
pqagent/pqmodel.py
pqagent/preprocessor.py
pqagent/sweeper.py
pqagent/config/base_config.yml
pqagent-0.0.12.dist-info/licenses/LICENSE
pqagent-0.0.12.dist-info/METADATA
pqagent-0.0.12.dist-info/WHEEL
pqagent-0.0.12.dist-info/top_level.txt
pqagent-0.0.12.dist-info/RECORD
