Metadata-Version: 2.4
Name: pqagent
Version: 0.0.12
Summary: A user friendly package for training quality prediction models
Author-email: Nils Klasen <likeable.versed-78@icloud.com>
License-Expression: MIT
Project-URL: Homepage, https://git-ce.rwth-aachen.de/kls/pqagent
Project-URL: Documentation, https://pqagent-e03a29.pages.git-ce.rwth-aachen.de
Project-URL: Issues, https://git-ce.rwth-aachen.de/kls/pqagent/-/issues
Classifier: Programming Language :: Python :: 3.11
Classifier: Programming Language :: Python :: 3.12
Classifier: Operating System :: OS Independent
Requires-Python: <4,>=3.11
License-File: LICENSE
Requires-Dist: dwrappr>=0.0.12
Requires-Dist: pandas>=2.0.0
Requires-Dist: scikit-learn>=1.6.0
Requires-Dist: ray>=2.0.0
Requires-Dist: matplotlib>=3.0.0
Requires-Dist: torch
Requires-Dist: pyarrow
Dynamic: license-file
